fallenleaf/di/__init__.py
fallenleaf/di/container.py
fallenleaf/di/declarative.py
fallenleaf/di/example.py
fallenleaf/di/exceptions.py
fallenleaf/di/provider.py
fallenleaf/di/types.py
fallenleaf/utils/__init__.py
fallenleaf/utils/configurable.py
fallenleaf/utils/multidict.py
fallenleaf/utils/switch.py
fallenleaf-0.5.2.dist-info/METADATA
fallenleaf-0.5.2.dist-info/WHEEL
fallenleaf-0.5.2.dist-info/top_level.txt
fallenleaf-0.5.2.dist-info/RECORD
