Metadata-Version: 2.1
Name: fallenleaf
Version: 0.5.2
Summary: Fallenleaf is simple dependecy injection container
Home-page: https://github.com/AfterSchoolTeaParty/fallenleaf
Author: nakanoyoichi83
License: MIT
Platform: UNKNOWN
Requires-Python: >=3.8
Requires-Dist: werkzeug
